{"expireTime":9007200823033807000,"key":"gatsby-plugin-mdx-entire-payload-fb53b87fba1b2fc5d3b24961e18716a1-","val":{"mdast":{"type":"root","children":[{"type":"import","value":"import DefaultLayout from \"/Users/michael/Documents/GitHub/quill/.docz/node_modules/gatsby-theme-docz/src/base/Layout.js\"","position":{"start":{"line":3,"column":1,"offset":2},"end":{"line":3,"column":122,"offset":123},"indent":[]}},{"type":"export","default":true,"value":"export default DefaultLayout","position":{"start":{"line":5,"column":1,"offset":125},"end":{"line":5,"column":29,"offset":153},"indent":[]}},{"type":"import","value":"import { Playground, Props } from \"docz\";","position":{"start":{"line":8,"column":1,"offset":156},"end":{"line":8,"column":42,"offset":197},"indent":[]}},{"type":"import","value":"import Label from \"./\";","position":{"start":{"line":10,"column":1,"offset":199},"end":{"line":10,"column":24,"offset":222},"indent":[]}},{"type":"import","value":"import { Colors } from \"../../foundations/Color\"","position":{"start":{"line":12,"column":1,"offset":224},"end":{"line":12,"column":49,"offset":272},"indent":[]}},{"type":"heading","depth":1,"children":[{"type":"text","value":"Label","position":{"start":{"line":14,"column":3,"offset":276},"end":{"line":14,"column":8,"offset":281},"indent":[]}}],"position":{"start":{"line":14,"column":1,"offset":274},"end":{"line":14,"column":8,"offset":281},"indent":[]}},{"type":"heading","depth":2,"children":[{"type":"text","value":"Summary","position":{"start":{"line":16,"column":4,"offset":286},"end":{"line":16,"column":11,"offset":293},"indent":[]}}],"position":{"start":{"line":16,"column":1,"offset":283},"end":{"line":16,"column":11,"offset":293},"indent":[]}},{"type":"paragraph","children":[{"type":"text","value":"The Label is used to give components additional context.","position":{"start":{"line":18,"column":1,"offset":295},"end":{"line":18,"column":57,"offset":351},"indent":[]}}],"position":{"start":{"line":18,"column":1,"offset":295},"end":{"line":18,"column":57,"offset":351},"indent":[]}},{"type":"heading","depth":2,"children":[{"type":"text","value":"Example","position":{"start":{"line":20,"column":4,"offset":356},"end":{"line":20,"column":11,"offset":363},"indent":[]}}],"position":{"start":{"line":20,"column":1,"offset":353},"end":{"line":20,"column":11,"offset":363},"indent":[]}},{"type":"heading","depth":3,"children":[{"type":"text","value":"Default Label","position":{"start":{"line":22,"column":5,"offset":369},"end":{"line":22,"column":18,"offset":382},"indent":[]}}],"position":{"start":{"line":22,"column":1,"offset":365},"end":{"line":22,"column":18,"offset":382},"indent":[]}},{"type":"jsx","value":"<Playground>\n  <Label children=\"Label Text\"/>\n</Playground>","position":{"start":{"line":24,"column":1,"offset":384},"end":{"line":26,"column":14,"offset":443},"indent":[1,1]}},{"type":"heading","depth":3,"children":[{"type":"text","value":"Default Label","position":{"start":{"line":28,"column":5,"offset":449},"end":{"line":28,"column":18,"offset":462},"indent":[]}}],"position":{"start":{"line":28,"column":1,"offset":445},"end":{"line":28,"column":18,"offset":462},"indent":[]}},{"type":"jsx","value":"<Playground>\n  <Label children=\"Label Text\" color={Colors.slate} />\n</Playground>","position":{"start":{"line":30,"column":1,"offset":464},"end":{"line":32,"column":14,"offset":545},"indent":[1,1]}},{"type":"heading","depth":2,"children":[{"type":"text","value":"Props","position":{"start":{"line":34,"column":4,"offset":550},"end":{"line":34,"column":9,"offset":555},"indent":[]}}],"position":{"start":{"line":34,"column":1,"offset":547},"end":{"line":34,"column":9,"offset":555},"indent":[]}},{"type":"jsx","value":"<Props of={Label} />","position":{"start":{"line":36,"column":1,"offset":557},"end":{"line":36,"column":21,"offset":577},"indent":[]}},{"type":"export","value":"export const _frontmatter = {}","position":{"start":{"line":39,"column":1,"offset":580},"end":{"line":39,"column":31,"offset":610},"indent":[]}}],"position":{"start":{"line":1,"column":1,"offset":0},"end":{"line":39,"column":31,"offset":610}}},"scopeImports":[],"scopeIdentifiers":[],"rawMDXOutput":"/* @jsx mdx */\nimport { mdx } from '@mdx-js/react';\n/* @jsx mdx */\nimport DefaultLayout from \"/Users/michael/Documents/GitHub/quill/.docz/node_modules/gatsby-theme-docz/src/base/Layout.js\"\nimport { Playground, Props } from \"docz\";\nimport Label from \"./\";\nimport { Colors } from \"../../foundations/Color\"\nexport const _frontmatter = {};\nconst makeShortcode = name => function MDXDefaultShortcode(props) {\n  console.warn(\"Component \" + name + \" was not imported, exported, or provided by MDXProvider as global scope\")\n  return <div {...props}/>\n};\n\nconst layoutProps = {\n  _frontmatter\n};\nconst MDXLayout = DefaultLayout\nexport default function MDXContent({\n  components,\n  ...props\n}) {\n  return <MDXLayout {...layoutProps} {...props} components={components} mdxType=\"MDXLayout\">\n\n\n\n\n\n    <h1 {...{\n      \"id\": \"label\"\n    }}>{`Label`}</h1>\n    <h2 {...{\n      \"id\": \"summary\"\n    }}>{`Summary`}</h2>\n    <p>{`The Label is used to give components additional context.`}</p>\n    <h2 {...{\n      \"id\": \"example\"\n    }}>{`Example`}</h2>\n    <h3 {...{\n      \"id\": \"default-label\"\n    }}>{`Default Label`}</h3>\n    <Playground __position={0} __code={'<Label children=\\\"Label Text\\\" />'} __scope={{\n      props,\n      DefaultLayout,\n      Playground,\n      Props,\n      Label,\n      Colors\n    }} mdxType=\"Playground\">\n  <Label children=\"Label Text\" mdxType=\"Label\" />\n    </Playground>\n    <h3 {...{\n      \"id\": \"default-label-1\"\n    }}>{`Default Label`}</h3>\n    <Playground __position={1} __code={'<Label children=\\\"Label Text\\\" color={Colors.slate} />'} __scope={{\n      props,\n      DefaultLayout,\n      Playground,\n      Props,\n      Label,\n      Colors\n    }} mdxType=\"Playground\">\n  <Label children=\"Label Text\" color={Colors.slate} mdxType=\"Label\" />\n    </Playground>\n    <h2 {...{\n      \"id\": \"props\"\n    }}>{`Props`}</h2>\n    <Props of={Label} mdxType=\"Props\" />\n\n    </MDXLayout>;\n}\n\n;\nMDXContent.isMDXComponent = true;"}}